<annotation>
	<folder>flanged_test</folder>
	<filename>bb0805dp4-s15_revc.jpg</filename>
	<path>C:\Users\Kaushik Koilada\Documents\Desk\Projects\ggbearings\testImages\flanged_test\bb0805dp4-s15_revc.jpg</path>
	<source>
		<database>Unknown</database>
	</source>
	<size>
		<width>8268</width>
		<height>5846</height>
		<depth>1</depth>
	</size>
	<segmented>0</segmented>
	<object>
		<name>Flange Length and Thickness</name>
		<pose>Unspecified</pose>
		<truncated>0</truncated>
		<difficult>0</difficult>
		<bndbox>
			<xmin>474</xmin>
			<ymin>1236</ymin>
			<xmax>1768</xmax>
			<ymax>1736</ymax>
		</bndbox>
	</object>
	<object>
		<name>Flange Diameter</name>
		<pose>Unspecified</pose>
		<truncated>0</truncated>
		<difficult>0</difficult>
		<bndbox>
			<xmin>255</xmin>
			<ymin>1848</ymin>
			<xmax>1068</xmax>
			<ymax>2554</ymax>
		</bndbox>
	</object>
	<object>
		<name>Flange Bend Radius</name>
		<pose>Unspecified</pose>
		<truncated>0</truncated>
		<difficult>0</difficult>
		<bndbox>
			<xmin>887</xmin>
			<ymin>2323</ymin>
			<xmax>1855</xmax>
			<ymax>2786</ymax>
		</bndbox>
	</object>
	<object>
		<name>ID Corner Break</name>
		<pose>Unspecified</pose>
		<truncated>0</truncated>
		<difficult>0</difficult>
		<bndbox>
			<xmin>2237</xmin>
			<ymin>3711</ymin>
			<xmax>2868</xmax>
			<ymax>4292</ymax>
		</bndbox>
	</object>
	<object>
		<name>OD Chamfer Angle</name>
		<pose>Unspecified</pose>
		<truncated>0</truncated>
		<difficult>0</difficult>
		<bndbox>
			<xmin>1249</xmin>
			<ymin>4211</ymin>
			<xmax>1599</xmax>
			<ymax>4942</ymax>
		</bndbox>
	</object>
	<object>
		<name>OD Chamfer Length</name>
		<pose>Unspecified</pose>
		<truncated>0</truncated>
		<difficult>0</difficult>
		<bndbox>
			<xmin>2012</xmin>
			<ymin>4692</ymin>
			<xmax>2999</xmax>
			<ymax>4923</ymax>
		</bndbox>
	</object>
</annotation>
